Metadata-Version: 2.4
Name: nexaroa
Version: 0.2.56
Summary: Decentralized AI Network
Author-email: NeuroShard Team <team@neuroshard.com>
License-Expression: Apache-2.0
Project-URL: Homepage, https://neuroshard.com
Project-URL: Documentation, https://docs.neuroshard.com
Project-URL: Repository, https://github.com/Nexaroa/neuroshard
Project-URL: Issues, https://github.com/Nexaroa/neuroshard/issues
Keywords: ai,machine-learning,distributed-computing,blockchain,llm,neural-network,decentralized,training
Classifier: Development Status :: 4 - Beta
Classifier: Intended Audience :: Developers
Classifier: Intended Audience :: Science/Research
Classifier: Operating System :: OS Independent
Classifier: Programming Language :: Python :: 3
Classifier: Programming Language :: Python :: 3.9
Classifier: Programming Language :: Python :: 3.10
Classifier: Programming Language :: Python :: 3.11
Classifier: Programming Language :: Python :: 3.12
Classifier: Topic :: Scientific/Engineering :: Artificial Intelligence
Classifier: Topic :: System :: Distributed Computing
Requires-Python: >=3.9
License-File: LICENSE
Requires-Dist: transformers>=4.30.0
Requires-Dist: fastapi>=0.100.0
Requires-Dist: uvicorn>=0.23.0
Requires-Dist: requests>=2.28.0
Requires-Dist: pydantic>=2.0.0
Requires-Dist: psutil>=5.9.0
Requires-Dist: grpcio>=1.50.0
Requires-Dist: protobuf>=4.21.0
Requires-Dist: safetensors>=0.3.0
Requires-Dist: cryptography>=41.0.0
Requires-Dist: mnemonic>=0.20
Requires-Dist: jinja2>=3.1.0
Provides-Extra: gpu
Requires-Dist: torch>=2.0.0; extra == "gpu"
Provides-Extra: gui
Requires-Dist: customtkinter>=5.2.0; extra == "gui"
Requires-Dist: Pillow>=9.0.0; extra == "gui"
Requires-Dist: pystray>=0.19.0; extra == "gui"
Provides-Extra: full
Requires-Dist: torch>=2.0.0; extra == "full"
Requires-Dist: customtkinter>=5.2.0; extra == "full"
Requires-Dist: Pillow>=9.0.0; extra == "full"
Requires-Dist: pystray>=0.19.0; extra == "full"
Provides-Extra: dev
Requires-Dist: pytest>=7.0.0; extra == "dev"
Requires-Dist: pytest-asyncio>=0.21.0; extra == "dev"
Requires-Dist: black>=23.0.0; extra == "dev"
Requires-Dist: ruff>=0.0.280; extra == "dev"
Requires-Dist: torch>=2.0.0; extra == "dev"
Dynamic: license-file
